atomsmltr/__init__.py
atomsmltr/atoms/__init__.py
atomsmltr/atoms/collection/__init__.py
atomsmltr/atoms/collection/rubidium.py
atomsmltr/atoms/collection/strontium.py
atomsmltr/atoms/collection/ytterbium.py
atomsmltr/atoms/generic.py
atomsmltr/atoms/transitions.py
atomsmltr/datapipe/__init__.py
atomsmltr/environment/__init__.py
atomsmltr/environment/envbase.py
atomsmltr/environment/fields/__init__.py
atomsmltr/environment/fields/force/__init__.py
atomsmltr/environment/fields/force/force.py
atomsmltr/environment/fields/generic.py
atomsmltr/environment/fields/interpolated.py
atomsmltr/environment/fields/magnetic/__init__.py
atomsmltr/environment/fields/magnetic/magnetic.py
atomsmltr/environment/fields/magnetic/magpylib.py
atomsmltr/environment/lasers/__init__.py
atomsmltr/environment/lasers/beams.py
atomsmltr/environment/lasers/polarization.py
atomsmltr/environment/modifiers.py
atomsmltr/environment/zones/__init__.py
atomsmltr/environment/zones/generic.py
atomsmltr/environment/zones/limits.py
atomsmltr/environment/zones/volumes.py
atomsmltr/examples/__init__.py
atomsmltr/examples/atomic_fountain.py
atomsmltr/examples/chen2021.py
atomsmltr/examples/feng2024.py
atomsmltr/simulation/__init__.py
atomsmltr/simulation/configurator.py
atomsmltr/simulation/simulator/__init__.py
atomsmltr/simulation/simulator/deterministic.py
atomsmltr/simulation/simulator/scipy.py
atomsmltr/simulation/simulator/simbase.py
atomsmltr/simulation/simulator/stochastic.py
atomsmltr/utils/__init__.py
atomsmltr/utils/infostring.py
atomsmltr/utils/misc.py
atomsmltr/utils/plotter/__init__.py
atomsmltr/utils/plotter/plotter.py
atomsmltr/utils/plotter/tools.py
atomsmltr/utils/wisdom.py
atomsmltr-0.1.4.dist-info/LICENSE
atomsmltr-0.1.4.dist-info/METADATA
atomsmltr-0.1.4.dist-info/WHEEL
atomsmltr-0.1.4.dist-info/RECORD
