Metadata-Version: 2.3
Name: atomsmltr
Version: 0.1.4
Summary: Laser cooling and trapping simulation tool
License: GPL-3.0-or-later
Author: Alexandre Dareau
Author-email: alexandre.dareau@protonmail.com
Maintainer: Alexandre Dareau
Maintainer-email: alexandre.dareau@protonmail.com
Requires-Python: >=3.12
Classifier: Development Status :: 4 - Beta
Classifier: Intended Audience :: Science/Research
Classifier: Intended Audience :: Education
Classifier: Topic :: Scientific/Engineering :: Physics
Requires-Dist: black (>=24.10.0,<25.0.0)
Requires-Dist: matplotlib (>=3.10.0,<4.0.0)
Requires-Dist: scipy (>=1.15.1,<2.0.0)
Requires-Dist: tqdm (>=4.67.1,<5.0.0)
Project-URL: Homepage, https://atomsmltr.readthedocs.io
Project-URL: Issues, https://github.com/adareau/atomSmltr/issues
Project-URL: Repository, https://github.com/adareau/atomSmltr
